cryptic_sdk/__init__.py
cryptic_sdk/client.py
cryptic_sdk/expeptions.py
cryptic_sdk/models/__init__.py
cryptic_sdk/models/device.py
cryptic_sdk/models/transaction.py
cryptic_sdk/models/user.py
cryptic_sdk/models/wallet.py
cryptic_sdk-1.1.1.dist-info/LICENSE
cryptic_sdk-1.1.1.dist-info/METADATA
cryptic_sdk-1.1.1.dist-info/WHEEL
cryptic_sdk-1.1.1.dist-info/top_level.txt
cryptic_sdk-1.1.1.dist-info/RECORD
