Metadata-Version: 2.1
Name: cryptic-sdk
Version: 1.1.1
Summary: A Cryptic SDK for Python
Home-page: https://github.com/Tert0/cryptic-sdk
Author: Tert0
License: MIT
Platform: UNKNOWN
Requires-Python: >=3.5
Requires-Dist: websocket-client
